{
  "$schema": "https://developer.microsoft.com/json-schemas/fabric/item/report/definition/visualContainer/2.10.0/schema.json",
  "name": "0534363428708c137f60",
  "position": {
    "x": 416.74418604651163,
    "y": 76.899224806201545,
    "z": 3000,
    "height": 160,
    "width": 240.62015503875969,
    "tabOrder": 3000
  },
  "visual": {
    "visualType": "cardVisual",
    "query": {
      "queryState": {
        "Data": {
          "projections": [
            {
              "field": {
                "Measure": {
                  "Expression": {
                    "SourceRef": {
                      "Entity": "public pipeline_audit"
                    }
                  },
                  "Property": "Success Rate %"
                }
              },
              "queryRef": "public pipeline_audit.Success Rate %",
              "nativeQueryRef": "Success Rate %"
            }
          ]
        }
      },
      "sortDefinition": {
        "sort": [
          {
            "field": {
              "Measure": {
                "Expression": {
                  "SourceRef": {
                    "Entity": "public pipeline_audit"
                  }
                },
                "Property": "Success Rate %"
              }
            },
            "direction": "Descending"
          }
        ],
        "isDefaultSort": true
      }
    },
    "visualContainerObjects": {
      "title": [
        {
          "properties": {
            "show": {
              "expr": {
                "Literal": {
                  "Value": "true"
                }
              }
            },
            "text": {
              "expr": {
                "Literal": {
                  "Value": "'✅ Success Rate'"
                }
              }
            },
            "fontSize": {
              "expr": {
                "Literal": {
                  "Value": "12D"
                }
              }
            },
            "fontFamily": {
              "expr": {
                "Literal": {
                  "Value": "'Segoe UI Semibold'"
                }
              }
            }
          }
        }
      ],
      "background": [
        {
          "properties": {
            "show": {
              "expr": {
                "Literal": {
                  "Value": "true"
                }
              }
            },
            "transparency": {
              "expr": {
                "Literal": {
                  "Value": "0D"
                }
              }
            }
          }
        }
      ],
      "border": [
        {
          "properties": {
            "show": {
              "expr": {
                "Literal": {
                  "Value": "true"
                }
              }
            },
            "radius": {
              "expr": {
                "Literal": {
                  "Value": "8D"
                }
              }
            }
          }
        }
      ],
      "padding": [
        {
          "properties": {
            "top": {
              "expr": {
                "Literal": {
                  "Value": "6D"
                }
              }
            },
            "right": {
              "expr": {
                "Literal": {
                  "Value": "6D"
                }
              }
            },
            "bottom": {
              "expr": {
                "Literal": {
                  "Value": "6D"
                }
              }
            },
            "left": {
              "expr": {
                "Literal": {
                  "Value": "6D"
                }
              }
            }
          }
        }
      ]
    },
    "drillFilterOtherVisuals": true
  },
  "filterConfig": {
    "filters": [
      {
        "name": "c6d9dbf05db30c760b14",
        "field": {
          "Measure": {
            "Expression": {
              "SourceRef": {
                "Entity": "public pipeline_audit"
              }
            },
            "Property": "Success Rate %"
          }
        },
        "type": "Advanced"
      }
    ]
  }
}